{
  "id": "deck_M03",
  "title": "現代社会と健康(下)",
  "isPurchased": false,
  "units": [
    {
      "id": "unit_mental_disorders_prevention",
      "title": "精神疾患の予防",
      "cards": [
        {
          "question": "精神疾患の予防で重視される考え方はどれか？",
          "choices": [
            "ストレスや不調を早く察知して対処する",
            "症状が悪化するまで放置する",
            "精神疾患を完全に排除しようとする",
            "薬だけで解決しようとする"
          ],
          "answerIndex": 0,
          "explanation": "早期発見とセルフケアにより重症化を防ぐことが重要とされている。",
          "tags": [
            "予防",
            "早期発見",
            "セルフケア"
          ],
          "importance": 1,
          "isPremium": false
        },
        {
          "question": "精神疾患の早期発見において大切なのはどれか？",
          "choices": [
            "心や体の変化に気づくこと",
            "家族に隠すこと",
            "気分を紛らわせること",
            "病気を我慢すること"
          ],
          "answerIndex": 0,
          "explanation": "自分の変化を自覚し周囲に相談することが早期発見につながる。",
          "tags": [
            "早期発見",
            "自己理解",
            "相談"
          ],
          "importance": 1,
          "isPremium": false
        },
        {
          "question": "セルフケアの具体的な内容として適切なのはどれか？",
          "choices": [
            "睡眠・食事・運動のリズムを整える",
            "常に他人と比べる",
            "感情を抑え込む",
            "我慢を続ける"
          ],
          "answerIndex": 0,
          "explanation": "基本的な生活習慣を整えることがセルフケアの基本である。",
          "tags": [
            "セルフケア",
            "生活習慣",
            "健康行動"
          ],
          "importance": 1,
          "isPremium": false
        },
        {
          "question": "心の不調を感じたときにまず行うべき対応はどれか？",
          "choices": [
            "信頼できる人に相談する",
            "一人で抱え込む",
            "他人を責める",
            "睡眠を減らして頑張る"
          ],
          "answerIndex": 0,
          "explanation": "早期に相談することで適切な支援や治療につながる。",
          "tags": [
            "相談",
            "支援",
            "早期対応"
          ],
          "importance": 1,
          "isPremium": false
        },
        {
          "question": "周囲の人ができる支援として適切なのはどれか？",
          "choices": [
            "話を聴き共感を示す",
            "叱って励ます",
            "無理に明るくふるまわせる",
            "距離を置く"
          ],
          "answerIndex": 0,
          "explanation": "傾聴と共感により安心感を与えることが支援につながる。",
          "tags": [
            "支援",
            "共感",
            "傾聴"
          ],
          "importance": 2,
          "isPremium": false
        },
        {
          "question": "精神疾患の治療・回復で重要とされる考え方はどれか？",
          "choices": [
            "リカバリー（回復）を支える",
            "病気を完全に治すことだけを目的にする",
            "本人の意見を無視する",
            "薬だけに頼る"
          ],
          "answerIndex": 0,
          "explanation": "リカバリーは本人の生活の質や自立を重視した回復の考え方である。",
          "tags": [
            "リカバリー",
            "回復",
            "支援"
          ],
          "importance": 2,
          "isPremium": false
        },
        {
          "question": "リカバリーのうち「パーソナル・リカバリー」の特徴はどれか？",
          "choices": [
            "自分らしく生きることを重視する",
            "症状を完全に消すことを目的とする",
            "医療機関での処置に限定される",
            "薬物療法を中心とする"
          ],
          "answerIndex": 0,
          "explanation": "パーソナル・リカバリーは本人の価値観や生き方を尊重した回復を目指す。",
          "tags": [
            "リカバリー",
            "自己実現",
            "生活の質"
          ],
          "importance": 3,
          "isPremium": true
        },
        {
          "question": "スティグマとは何を指すか？",
          "choices": [
            "精神疾患などに対する偏見や差別",
            "治療に使う薬の名前",
            "心理的ストレスの一種",
            "病気の初期症状"
          ],
          "answerIndex": 0,
          "explanation": "スティグマとは精神疾患などに対する社会的な偏見・差別のことをいう。",
          "tags": [
            "スティグマ",
            "偏見",
            "社会問題"
          ],
          "importance": 2,
          "isPremium": true
        },
        {
          "question": "アンチスティグマの取組として適切なのはどれか？",
          "choices": [
            "正しい知識を広める活動",
            "病気の人を避ける",
            "偏見を強める発言をする",
            "沈黙を守る"
          ],
          "answerIndex": 0,
          "explanation": "精神疾患への理解を広げる教育や啓発活動がアンチスティグマにつながる。",
          "tags": [
            "アンチスティグマ",
            "啓発",
            "社会支援"
          ],
          "importance": 2,
          "isPremium": true
        },
        {
          "question": "精神疾患の予防における「3つの予防」のうち、誰もが対象となるものはどれか？",
          "choices": [
            "一次予防（普遍予防）",
            "二次予防（選択予防）",
            "三次予防（特定予防）",
            "個別予防"
          ],
          "answerIndex": 0,
          "explanation": "一次予防はすべての人を対象に心の健康づくりを促す予防である。",
          "tags": [
            "一次予防",
            "普遍予防",
            "健康教育"
          ],
          "importance": 3,
          "isPremium": true
        },
        {
          "question": "ストレスのサインとして当てはまるものはどれか？",
          "choices": [
            "眠れない・食欲がない",
            "気分が良い",
            "集中できる",
            "意欲的になる"
          ],
          "answerIndex": 0,
          "explanation": "ストレスが強くなると睡眠や食欲に変化が現れることがある。",
          "tags": [
            "ストレス",
            "サイン",
            "心身の変化"
          ],
          "importance": 1,
          "isPremium": true
        },
        {
          "question": "精神疾患の発症に関わるリスクとして正しいものはどれか？",
          "choices": [
            "過度なストレスや生活習慣の乱れ",
            "運動のしすぎ",
            "笑いすぎ",
            "寒暖差"
          ],
          "answerIndex": 0,
          "explanation": "ストレスや不規則な生活が心の不調を引き起こす要因となる。",
          "tags": [
            "リスク",
            "生活習慣",
            "ストレス"
          ],
          "importance": 1,
          "isPremium": true
        },
        {
          "question": "心の不調を早く見つけるために有効な行動はどれか？",
          "choices": [
            "気分や体調を日記などで記録する",
            "無理に頑張り続ける",
            "落ち込みを隠す",
            "人を避ける"
          ],
          "answerIndex": 0,
          "explanation": "自分の変化を客観的に把握することで早期発見につながる。",
          "tags": [
            "セルフモニタリング",
            "早期発見",
            "自己理解"
          ],
          "importance": 2,
          "isPremium": true
        },
        {
          "question": "周囲の人が相談を受ける際に大切な態度はどれか？",
          "choices": [
            "批判せずに話を聴く",
            "すぐに解決策を押しつける",
            "冗談にして軽く流す",
            "相手を責める"
          ],
          "answerIndex": 0,
          "explanation": "相手を受け止め共感的に聴くことで安心感を与えることができる。",
          "tags": [
            "傾聴",
            "支援",
            "相談"
          ],
          "importance": 2,
          "isPremium": true
        },
        {
          "question": "精神疾患の治療で医療機関が果たす主な役割はどれか？",
          "choices": [
            "診断と専門的治療",
            "生活習慣の乱れを助長する",
            "社会的偏見を広げる",
            "自宅での我慢を勧める"
          ],
          "answerIndex": 0,
          "explanation": "医療機関は専門的な診断と治療を通じて回復を支援する。",
          "tags": [
            "医療",
            "治療",
            "支援"
          ],
          "importance": 1,
          "isPremium": true
        },
        {
          "question": "心の健康づくりのために重要な社会的要素はどれか？",
          "choices": [
            "安心して相談できる人間関係",
            "厳しい競争環境",
            "孤立した生活",
            "他者への無関心"
          ],
          "answerIndex": 0,
          "explanation": "支え合える関係がストレスを緩和し心の健康に寄与する。",
          "tags": [
            "社会的支援",
            "人間関係",
            "健康"
          ],
          "importance": 2,
          "isPremium": true
        },
        {
          "question": "心の健康問題への対応で学校が果たすべき役割はどれか？",
          "choices": [
            "相談体制やカウンセリングの整備",
            "生徒の悩みを無視する",
            "不登校を叱責で解決する",
            "成績のみ重視する"
          ],
          "answerIndex": 0,
          "explanation": "学校は生徒の心の不調を早期に支援できる体制づくりが重要である。",
          "tags": [
            "学校支援",
            "相談体制",
            "予防"
          ],
          "importance": 2,
          "isPremium": true
        },
        {
          "question": "ストレス対処の方法として効果的なものはどれか？",
          "choices": [
            "好きな活動で気分転換する",
            "我慢し続ける",
            "暴飲暴食をする",
            "他人に八つ当たりする"
          ],
          "answerIndex": 0,
          "explanation": "趣味やリラックス活動で心をリセットすることが有効である。",
          "tags": [
            "ストレス対処",
            "リラックス",
            "セルフケア"
          ],
          "importance": 1,
          "isPremium": true
        },
        {
          "question": "「リカバリー」という言葉の意味として正しいものはどれか？",
          "choices": [
            "病気を抱えながらも自分らしく生きる",
            "完全に病気をなくすこと",
            "他人に依存すること",
            "社会から離れること"
          ],
          "answerIndex": 0,
          "explanation": "リカバリーは病気があっても自分らしい生活を取り戻す考え方である。",
          "tags": [
            "リカバリー",
            "回復",
            "自立"
          ],
          "importance": 2,
          "isPremium": true
        },
        {
          "question": "心の健康を守るための生活習慣として適切なのはどれか？",
          "choices": [
            "十分な睡眠をとる",
            "夜更かしを続ける",
            "朝食を抜く",
            "休日も仕事をする"
          ],
          "answerIndex": 0,
          "explanation": "睡眠・休養の確保は心身の回復に欠かせない。",
          "tags": [
            "生活習慣",
            "睡眠",
            "セルフケア"
          ],
          "importance": 1,
          "isPremium": true
        },
        {
          "question": "精神疾患の一次予防の例として適切なのはどれか？",
          "choices": [
            "ストレスマネジメント教育",
            "発症後の治療",
            "再発防止",
            "リハビリテーション"
          ],
          "answerIndex": 0,
          "explanation": "一次予防は発症を防ぐための教育や啓発活動を指す。",
          "tags": [
            "一次予防",
            "教育",
            "啓発"
          ],
          "importance": 3,
          "isPremium": true
        },
        {
          "question": "精神疾患の二次予防の目的はどれか？",
          "choices": [
            "早期発見・早期治療",
            "再発防止",
            "社会復帰支援",
            "完全治癒"
          ],
          "answerIndex": 0,
          "explanation": "二次予防は早い段階での対応により重症化を防ぐことを目的とする。",
          "tags": [
            "二次予防",
            "早期治療",
            "重症化防止"
          ],
          "importance": 3,
          "isPremium": true
        },
        {
          "question": "精神疾患の三次予防の内容として正しいものはどれか？",
          "choices": [
            "再発防止と社会復帰支援",
            "発症の予防",
            "教育による啓発",
            "ストレス解消"
          ],
          "answerIndex": 0,
          "explanation": "三次予防は治療後の再発を防ぎ社会復帰を支援する段階である。",
          "tags": [
            "三次予防",
            "再発防止",
            "社会復帰"
          ],
          "importance": 3,
          "isPremium": true
        },
        {
          "question": "周囲の支援者が気をつけるべき点はどれか？",
          "choices": [
            "相手のペースを尊重する",
            "焦って答えを出す",
            "感情的に反応する",
            "無理に元気づける"
          ],
          "answerIndex": 0,
          "explanation": "本人のペースを尊重し支援する姿勢が大切である。",
          "tags": [
            "支援",
            "共感",
            "傾聴"
          ],
          "importance": 2,
          "isPremium": true
        },
        {
          "question": "心の不調を抱える人への社会的支援として適切なのはどれか？",
          "choices": [
            "地域の相談窓口の活用",
            "孤立を促す",
            "偏見を広める",
            "批判的な発言をする"
          ],
          "answerIndex": 0,
          "explanation": "地域の保健センターなどの相談機関が支援の拠点となる。",
          "tags": [
            "社会的支援",
            "相談機関",
            "地域"
          ],
          "importance": 2,
          "isPremium": true
        },
        {
          "question": "精神疾患に関するスティグマの種類に含まれないものはどれか？",
          "choices": [
            "生理的スティグマ",
            "構造的スティグマ",
            "市民のスティグマ",
            "当事者の自己スティグマ"
          ],
          "answerIndex": 0,
          "explanation": "スティグマは社会構造・市民・当事者の3種類に分類される。",
          "tags": [
            "スティグマ",
            "偏見",
            "分類"
          ],
          "importance": 3,
          "isPremium": true
        },
        {
          "question": "精神疾患に関する「構造的スティグマ」とは何か？",
          "choices": [
            "社会制度や仕組みによる差別",
            "個人の思い込み",
            "家族の支援不足",
            "メディアの影響"
          ],
          "answerIndex": 0,
          "explanation": "構造的スティグマは制度や政策の中での差別を指す。",
          "tags": [
            "スティグマ",
            "社会構造",
            "差別"
          ],
          "importance": 3,
          "isPremium": true
        },
        {
          "question": "パーソナル・リカバリーの目標として適切なのはどれか？",
          "choices": [
            "自分らしい生き方を取り戻す",
            "薬をやめることだけ",
            "他人に依存する",
            "社会を避ける"
          ],
          "answerIndex": 0,
          "explanation": "パーソナル・リカバリーは自立と生活の質の向上を目指す。",
          "tags": [
            "リカバリー",
            "自立",
            "生活の質"
          ],
          "importance": 3,
          "isPremium": true
        },
        {
          "question": "学校での心の健康教育のねらいとして最も適切なのはどれか？",
          "choices": [
            "自他の心の不調に気づき支援できる力を育てる",
            "病気の人を見分ける力をつける",
            "ストレスを我慢する力を強める",
            "医師の役割を覚える"
          ],
          "answerIndex": 0,
          "explanation": "心の健康教育では気づきと支援のスキル育成が重視される。",
          "tags": [
            "教育",
            "気づき",
            "支援"
          ],
          "importance": 2,
          "isPremium": true
        },
        {
          "question": "心の健康づくりにおいて社会が目指すべき姿はどれか？",
          "choices": [
            "誰もが安心して暮らせる共生社会",
            "精神疾患の人を排除する社会",
            "競争を強める社会",
            "支援を減らす社会"
          ],
          "answerIndex": 0,
          "explanation": "心の不調や病があっても安心して暮らせる社会が目標である。",
          "tags": [
            "共生社会",
            "社会支援",
            "健康"
          ],
          "importance": 3,
          "isPremium": true
        }
      ]
    },
    {
      "id": "unit_mental_disorders_recovery",
      "title": "精神疾患からの回復",
      "cards": [
        {
          "question": "精神疾患の治療における専門家の役割はどれか？",
          "choices": [
            "精神科医による診断と治療",
            "家族による生活支援",
            "教師による指導",
            "友人による相談"
          ],
          "answerIndex": 0,
          "explanation": "精神科医は薬物療法や精神療法など専門的な治療を行う。",
          "tags": [
            "専門家",
            "治療",
            "精神科"
          ],
          "importance": 1,
          "isPremium": false
        },
        {
          "question": "カウンセリングの目的として正しいのはどれか？",
          "choices": [
            "悩みを共有し自己理解を深める",
            "他人の行動を指摘する",
            "精神薬を処方する",
            "ストレスを抑圧する"
          ],
          "answerIndex": 0,
          "explanation": "カウンセリングは対話を通じて悩みの整理や自己理解を促す心理的支援である。",
          "tags": [
            "カウンセリング",
            "支援",
            "心理"
          ],
          "importance": 1,
          "isPremium": false
        },
        {
          "question": "精神疾患の治療で用いられる薬の働きとして正しいのはどれか？",
          "choices": [
            "神経伝達のバランスを整える",
            "筋肉の成長を促す",
            "血圧を上げる",
            "体温を下げる"
          ],
          "answerIndex": 0,
          "explanation": "薬物療法では神経伝達物質の働きを調整し、症状を改善する。",
          "tags": [
            "薬物療法",
            "神経伝達",
            "治療"
          ],
          "importance": 1,
          "isPremium": false
        },
        {
          "question": "地域におけるケアの特徴として正しいのはどれか？",
          "choices": [
            "病院だけでなく地域全体で支える",
            "医師だけが対応する",
            "患者は隔離される",
            "家族のみが支援する"
          ],
          "answerIndex": 0,
          "explanation": "地域ケアは病院外でも支援体制を整え、生活の場で回復を支える取り組みである。",
          "tags": [
            "地域ケア",
            "支援",
            "社会資源"
          ],
          "importance": 1,
          "isPremium": false
        },
        {
          "question": "デイケアの目的として適切なのはどれか？",
          "choices": [
            "社会生活への復帰を支援する",
            "薬の副作用を調べる",
            "新しい治療法を研究する",
            "睡眠時間を管理する"
          ],
          "answerIndex": 0,
          "explanation": "デイケアは通所を通して生活リズムの改善や社会復帰を支援する活動である。",
          "tags": [
            "デイケア",
            "社会復帰",
            "支援"
          ],
          "importance": 2,
          "isPremium": false
        },
        {
          "question": "リワーク支援とはどのような支援か？",
          "choices": [
            "職場復帰を支援するプログラム",
            "家族関係の修復を目的とする支援",
            "睡眠障害の治療",
            "身体機能の訓練"
          ],
          "answerIndex": 0,
          "explanation": "リワーク支援はうつ病などで休職した人の職場復帰を支援する取組である。",
          "tags": [
            "リワーク",
            "職場復帰",
            "支援"
          ],
          "importance": 2,
          "isPremium": false
        },
        {
          "question": "ピアサポートの特徴として正しいのはどれか？",
          "choices": [
            "同じ経験をもつ人同士が支え合う",
            "専門家が一方的に助言する",
            "親が子を指導する",
            "企業が社員を監督する"
          ],
          "answerIndex": 0,
          "explanation": "ピアサポートは当事者同士が互いの経験を共有し支え合う活動である。",
          "tags": [
            "ピアサポート",
            "当事者",
            "支援"
          ],
          "importance": 2,
          "isPremium": true
        },
        {
          "question": "精神疾患からの回復過程で重要とされる支援はどれか？",
          "choices": [
            "医療・福祉・地域が連携する支援",
            "本人のみの努力",
            "家族だけの支援",
            "薬だけに頼る治療"
          ],
          "answerIndex": 0,
          "explanation": "回復には医療・福祉・地域などが連携した包括的支援が重要である。",
          "tags": [
            "回復支援",
            "連携",
            "包括ケア"
          ],
          "importance": 1,
          "isPremium": true
        },
        {
          "question": "精神疾患の早期発見のメリットとして正しいのはどれか？",
          "choices": [
            "再発のリスクを減らせる",
            "入院期間が長くなる",
            "症状が悪化しやすい",
            "治療が難しくなる"
          ],
          "answerIndex": 0,
          "explanation": "早期発見により適切な治療が早く行われ、再発や悪化の防止につながる。",
          "tags": [
            "早期発見",
            "再発予防",
            "治療"
          ],
          "importance": 2,
          "isPremium": true
        },
        {
          "question": "精神疾患に対する偏見を減らすために必要なことはどれか？",
          "choices": [
            "正しい知識と理解を広める",
            "患者を隔離する",
            "SNSで噂を共有する",
            "精神疾患を隠す"
          ],
          "answerIndex": 0,
          "explanation": "偏見をなくすには正しい知識をもとに理解を広げることが大切である。",
          "tags": [
            "偏見",
            "理解",
            "啓発"
          ],
          "importance": 3,
          "isPremium": true
        },
        {
          "question": "ストレスケアで重要とされる考え方はどれか？",
          "choices": [
            "問題への対処と感情の整理",
            "感情を抑え続ける",
            "他人の行動を批判する",
            "仕事を増やす"
          ],
          "answerIndex": 0,
          "explanation": "ストレスケアでは問題解決と感情の整理を通じて心の安定を図ることが大切である。",
          "tags": [
            "ストレス",
            "ケア",
            "対処"
          ],
          "importance": 2,
          "isPremium": true
        },
        {
          "question": "うつ病の症状として正しいものはどれか？",
          "choices": [
            "意欲の低下や眠れない状態",
            "体重の増加と活力の上昇",
            "集中力の向上",
            "社交性の増加"
          ],
          "answerIndex": 0,
          "explanation": "うつ病では気分の落ち込みや意欲低下、睡眠障害などがみられる。",
          "tags": [
            "うつ病",
            "症状",
            "精神疾患"
          ],
          "importance": 1,
          "isPremium": true
        },
        {
          "question": "パニック障害の特徴として適切なのはどれか？",
          "choices": [
            "突然の強い不安や動悸が起こる",
            "慢性的な睡眠不足が続く",
            "体が硬直して動けない",
            "記憶がなくなる"
          ],
          "answerIndex": 0,
          "explanation": "パニック障害は突発的な不安発作が特徴で、動悸や息苦しさが生じる。",
          "tags": [
            "パニック障害",
            "症状",
            "不安"
          ],
          "importance": 2,
          "isPremium": true
        },
        {
          "question": "統合失調症の症状として正しいものはどれか？",
          "choices": [
            "幻覚や妄想が生じる",
            "食欲が増える",
            "不眠が続く",
            "体温が上がる"
          ],
          "answerIndex": 0,
          "explanation": "統合失調症では現実の認識が乱れ、幻覚や妄想などの症状が見られる。",
          "tags": [
            "統合失調症",
            "症状",
            "精神疾患"
          ],
          "importance": 1,
          "isPremium": true
        },
        {
          "question": "精神疾患の治療で行われるリハビリテーションの目的はどれか？",
          "choices": [
            "社会生活の再構築",
            "薬の副作用を調べる",
            "家族関係を断つ",
            "記憶力を試す"
          ],
          "answerIndex": 0,
          "explanation": "リハビリテーションは社会生活を再び送れるように支援するために行う。",
          "tags": [
            "リハビリ",
            "社会生活",
            "回復"
          ],
          "importance": 2,
          "isPremium": true
        },
        {
          "question": "心の健康づくりにおいて大切な姿勢はどれか？",
          "choices": [
            "自分を大切にし他者を尊重する",
            "常に我慢をする",
            "問題を放置する",
            "他人に頼らない"
          ],
          "answerIndex": 0,
          "explanation": "自己理解と他者への思いやりをもつことが心の健康づくりにつながる。",
          "tags": [
            "心の健康",
            "自己理解",
            "尊重"
          ],
          "importance": 1,
          "isPremium": true
        },
        {
          "question": "地域社会の役割として適切なのはどれか？",
          "choices": [
            "回復後の生活を支援する",
            "病気を隠すよう促す",
            "医療を拒否させる",
            "家族だけで支える"
          ],
          "answerIndex": 0,
          "explanation": "地域社会は回復後の生活支援や社会参加を促す重要な役割を担う。",
          "tags": [
            "地域社会",
            "支援",
            "社会参加"
          ],
          "importance": 1,
          "isPremium": true
        },
        {
          "question": "家族が果たす支援として望ましいのはどれか？",
          "choices": [
            "本人を理解し寄り添う",
            "強く叱責して変化を促す",
            "常に監視する",
            "病気を話題にしない"
          ],
          "answerIndex": 0,
          "explanation": "家族は本人の立場を理解し、安心して相談できる環境を整えることが大切である。",
          "tags": [
            "家族支援",
            "理解",
            "共感"
          ],
          "importance": 2,
          "isPremium": true
        },
        {
          "question": "社会的スティグマとは何を指すか？",
          "choices": [
            "病気を持つ人への偏見や差別",
            "治療にかかる費用",
            "医療制度の仕組み",
            "健康保険証の管理"
          ],
          "answerIndex": 0,
          "explanation": "スティグマとは病気を理由とした差別や偏見のことで、回復の妨げとなる。",
          "tags": [
            "スティグマ",
            "偏見",
            "差別"
          ],
          "importance": 3,
          "isPremium": true
        },
        {
          "question": "精神疾患に関する正しい理解を広めるために必要な活動はどれか？",
          "choices": [
            "啓発活動",
            "監視活動",
            "隔離活動",
            "宣伝活動"
          ],
          "answerIndex": 0,
          "explanation": "社会全体で正しい知識と理解を広める啓発活動が求められる。",
          "tags": [
            "啓発",
            "教育",
            "理解"
          ],
          "importance": 3,
          "isPremium": true
        },
        {
          "question": "地域における包括的ケアの目的はどれか？",
          "choices": [
            "医療・福祉・地域が連携して支援する",
            "病気のある人を隔離する",
            "専門家だけで支える",
            "家族だけが支援する"
          ],
          "answerIndex": 0,
          "explanation": "包括的ケアは多職種・地域の連携により生活全体を支えることを目的とする。",
          "tags": [
            "包括ケア",
            "連携",
            "地域"
          ],
          "importance": 1,
          "isPremium": true
        },
        {
          "question": "精神疾患の再発を防ぐために大切なのはどれか？",
          "choices": [
            "規則正しい生活を保つ",
            "薬を自己判断で中止する",
            "治療を拒否する",
            "相談を避ける"
          ],
          "answerIndex": 0,
          "explanation": "再発予防には規則的な生活リズムを維持し、相談できる環境が重要である。",
          "tags": [
            "再発予防",
            "生活習慣",
            "相談"
          ],
          "importance": 2,
          "isPremium": true
        },
        {
          "question": "医療機関以外での支援の場として適切なのはどれか？",
          "choices": [
            "地域生活支援センター",
            "刑務所",
            "商業施設",
            "職業訓練校のみ"
          ],
          "answerIndex": 0,
          "explanation": "地域生活支援センターでは生活相談や就労支援などを行う。",
          "tags": [
            "地域支援",
            "センター",
            "生活相談"
          ],
          "importance": 2,
          "isPremium": true
        },
        {
          "question": "精神疾患からの回復における「当事者の力」とはどれか？",
          "choices": [
            "自らの経験をもとに支え合う力",
            "他人を支配する力",
            "問題を避ける力",
            "専門家を批判する力"
          ],
          "answerIndex": 0,
          "explanation": "当事者の経験を生かして他者と支え合うことが回復の一歩になる。",
          "tags": [
            "当事者",
            "経験",
            "回復"
          ],
          "importance": 2,
          "isPremium": true
        },
        {
          "question": "支援の過程で信頼関係を築くために大切なことはどれか？",
          "choices": [
            "相手の話をよく聴く",
            "指示だけを出す",
            "結果を急ぐ",
            "感情を無視する"
          ],
          "answerIndex": 0,
          "explanation": "傾聴によって信頼関係を築くことが支援の基本となる。",
          "tags": [
            "信頼関係",
            "傾聴",
            "支援"
          ],
          "importance": 1,
          "isPremium": true
        },
        {
          "question": "学校における心のケアで大切なことはどれか？",
          "choices": [
            "スクールカウンセラーに相談する",
            "成績を上げることを優先する",
            "病気を隠すようにする",
            "友人との関係を断つ"
          ],
          "answerIndex": 0,
          "explanation": "学校ではスクールカウンセラーなど専門家への相談が有効である。",
          "tags": [
            "学校",
            "相談",
            "心のケア"
          ],
          "importance": 2,
          "isPremium": true
        },
        {
          "question": "相談をためらう人に対して適切な行動はどれか？",
          "choices": [
            "安心して話せる環境をつくる",
            "強制的に話させる",
            "放置する",
            "周囲に広める"
          ],
          "answerIndex": 0,
          "explanation": "安心して話せる場を整えることが支援の第一歩となる。",
          "tags": [
            "相談支援",
            "環境",
            "傾聴"
          ],
          "importance": 2,
          "isPremium": true
        },
        {
          "question": "精神疾患の治療を受けるきっかけとして多いのはどれか？",
          "choices": [
            "家族や周囲の勧め",
            "本人の自覚なしに受診",
            "検診で発見される",
            "偶然の通院"
          ],
          "answerIndex": 0,
          "explanation": "周囲の勧めや助言によって治療につながることが多い。",
          "tags": [
            "受診",
            "家族",
            "支援"
          ],
          "importance": 2,
          "isPremium": true
        },
        {
          "question": "社会復帰を支援する仕組みとして正しいものはどれか？",
          "choices": [
            "就労支援",
            "休養指導",
            "服薬指導のみ",
            "運動療法のみ"
          ],
          "answerIndex": 0,
          "explanation": "就労支援は社会復帰を支える重要な支援制度である。",
          "tags": [
            "就労支援",
            "社会復帰",
            "支援"
          ],
          "importance": 2,
          "isPremium": true
        },
        {
          "question": "精神疾患からの回復で「支え合う社会」が目指す姿はどれか？",
          "choices": [
            "誰もが安心して生活できる地域社会",
            "病気を持つ人を排除する社会",
            "医療だけに頼る社会",
            "競争を強める社会"
          ],
          "answerIndex": 0,
          "explanation": "支え合う社会とは、病気の有無にかかわらず誰もが安心して暮らせる地域社会である。",
          "tags": [
            "支え合い",
            "地域社会",
            "共生"
          ],
          "importance": 3,
          "isPremium": true
        }
      ]
    },
    {
      "id": "unit_modern_infectious_diseases",
      "title": "現代の感染症",
      "cards": [
        {
          "question": "感染症とはどのような病気か？",
          "choices": [
            "病原体が人の体内に入り増えることで起こる病気",
            "生活習慣の乱れで起こる病気",
            "遺伝によって決まる病気",
            "外傷によって起こる病気"
          ],
          "answerIndex": 0,
          "explanation": "感染症は病原体が体内に侵入・増殖して起こる病気を指す。",
          "tags": [
            "定義",
            "病原体",
            "感染経路"
          ],
          "importance": 1,
          "isPremium": false
        },
        {
          "question": "感染症の原因となる病原体として正しいものはどれか？",
          "choices": [
            "細菌・ウイルス・真菌など",
            "酸素・二酸化炭素・窒素",
            "アミノ酸・糖質・脂質",
            "カルシウム・鉄・ナトリウム"
          ],
          "answerIndex": 0,
          "explanation": "感染症の原因は細菌やウイルスなどの病原体によるものである。",
          "tags": [
            "病原体",
            "感染",
            "種類"
          ],
          "importance": 1,
          "isPremium": false
        },
        {
          "question": "感染症の感染経路に含まれないものはどれか？",
          "choices": [
            "接触感染",
            "空気感染",
            "媒介動物感染",
            "遺伝感染"
          ],
          "answerIndex": 3,
          "explanation": "感染経路は接触・飛沫・空気などであり遺伝は含まれない。",
          "tags": [
            "感染経路",
            "接触",
            "飛沫"
          ],
          "importance": 1,
          "isPremium": false
        },
        {
          "question": "再興感染症とはどのような感染症か？",
          "choices": [
            "一度減少したが再び増加してきた感染症",
            "新たに発見された感染症",
            "抗生物質に耐性をもつ感染症",
            "人獣共通感染症のこと"
          ],
          "answerIndex": 0,
          "explanation": "再興感染症は一度減少したものの再び流行してきた感染症を指す。",
          "tags": [
            "再興感染症",
            "定義",
            "流行"
          ],
          "importance": 1,
          "isPremium": false
        },
        {
          "question": "新興感染症の例として正しいものはどれか？",
          "choices": [
            "エイズやSARSなど",
            "コレラやマラリア",
            "結核やはしか",
            "インフルエンザ（季節性）"
          ],
          "answerIndex": 0,
          "explanation": "新興感染症は近年になって出現した感染症である。",
          "tags": [
            "新興感染症",
            "例",
            "流行"
          ],
          "importance": 1,
          "isPremium": false
        },
        {
          "question": "エボラ出血熱の主な感染経路はどれか？",
          "choices": [
            "血液や体液との接触",
            "空気感染",
            "蚊による媒介",
            "水や食べ物からの感染"
          ],
          "answerIndex": 0,
          "explanation": "エボラ出血熱は患者の体液や血液との接触により感染する。",
          "tags": [
            "エボラ出血熱",
            "感染経路",
            "特徴"
          ],
          "importance": 2,
          "isPremium": false
        },
        {
          "question": "再興感染症が再び増加している要因として正しいものはどれか？",
          "choices": [
            "ワクチン接種率の低下や薬剤耐性菌の増加",
            "新しいウイルスの発見",
            "交通の発達",
            "人口減少"
          ],
          "answerIndex": 0,
          "explanation": "予防接種の低下や耐性菌の出現が再興感染症の増加につながっている。",
          "tags": [
            "再興感染症",
            "原因",
            "薬剤耐性"
          ],
          "importance": 2,
          "isPremium": true
        },
        {
          "question": "感染症の国際的な拡大を助長する要因はどれか？",
          "choices": [
            "交通や貿易の発達",
            "気温の低下",
            "人口の減少",
            "ワクチンの普及"
          ],
          "answerIndex": 0,
          "explanation": "交通や物流の発展により感染症は短期間で世界に拡大しやすくなる。",
          "tags": [
            "国際化",
            "感染拡大",
            "グローバル化"
          ],
          "importance": 2,
          "isPremium": true
        },
        {
          "question": "新型コロナウイルス感染症（COVID-19）の感染拡大を防ぐために行われた対策はどれか？",
          "choices": [
            "マスク着用や手洗い",
            "抗生物質の投与",
            "ビタミンの摂取",
            "紫外線照射"
          ],
          "answerIndex": 0,
          "explanation": "COVID-19では基本的感染対策としてマスクや手洗いが推奨された。",
          "tags": [
            "COVID-19",
            "感染対策",
            "予防"
          ],
          "importance": 1,
          "isPremium": true
        },
        {
          "question": "One Healthとはどのような考え方か？",
          "choices": [
            "人・動物・環境を一体として健康を守る考え方",
            "人の健康のみを重視する考え方",
            "医療従事者の連携を重視する考え方",
            "ウイルスの除去を目的とする考え方"
          ],
          "answerIndex": 0,
          "explanation": "One Healthは人と動物と環境の健康を総合的にとらえる考え方である。",
          "tags": [
            "OneHealth",
            "SDH",
            "国際保健"
          ],
          "importance": 3,
          "isPremium": true
        },
        {
          "question": "インフルエンザの主な感染経路はどれか？",
          "choices": [
            "飛沫感染",
            "接触感染",
            "媒介動物感染",
            "経口感染"
          ],
          "answerIndex": 0,
          "explanation": "インフルエンザは感染者の咳やくしゃみの飛沫によって感染が広がる。",
          "tags": [
            "インフルエンザ",
            "感染経路",
            "飛沫"
          ],
          "importance": 1,
          "isPremium": true
        },
        {
          "question": "新型インフルエンザが問題視される理由はどれか？",
          "choices": [
            "多くの人が免疫をもたないため流行しやすい",
            "感染力が弱く流行しにくい",
            "動物にしか感染しない",
            "季節的にしか発生しない"
          ],
          "answerIndex": 0,
          "explanation": "新型インフルエンザは新しい型のウイルスで多くの人が免疫をもたないため流行しやすい。",
          "tags": [
            "新型インフルエンザ",
            "免疫",
            "流行"
          ],
          "importance": 1,
          "isPremium": true
        },
        {
          "question": "再興感染症の具体例として正しいものはどれか？",
          "choices": [
            "結核やマラリア",
            "SARSやエボラ出血熱",
            "HIVやCOVID-19",
            "食中毒"
          ],
          "answerIndex": 0,
          "explanation": "再興感染症には結核やマラリアなど一度減少したが再び増えた感染症がある。",
          "tags": [
            "再興感染症",
            "例",
            "流行"
          ],
          "importance": 1,
          "isPremium": true
        },
        {
          "question": "新興感染症が出現する要因として適切なのはどれか？",
          "choices": [
            "自然環境の変化や人間活動の拡大",
            "医療技術の発達",
            "出生率の低下",
            "気温の低下"
          ],
          "answerIndex": 0,
          "explanation": "森林開発や人口移動など人間活動の拡大が新興感染症の出現を招く。",
          "tags": [
            "新興感染症",
            "原因",
            "環境"
          ],
          "importance": 2,
          "isPremium": true
        },
        {
          "question": "WHOが定めた感染症対策の国際的な枠組みはどれか？",
          "choices": [
            "国際保健規則（IHR）",
            "京都議定書",
            "SDGs",
            "生物多様性条約"
          ],
          "answerIndex": 0,
          "explanation": "IHRは感染症の国際的な流行に対して各国が協力して対応する枠組みである。",
          "tags": [
            "WHO",
            "国際保健",
            "感染対策"
          ],
          "importance": 2,
          "isPremium": true
        },
        {
          "question": "マラリアの感染経路はどれか？",
          "choices": [
            "ハマダラカによる媒介",
            "咳やくしゃみによる飛沫",
            "水や食物からの感染",
            "人から人への直接感染"
          ],
          "answerIndex": 0,
          "explanation": "マラリアはハマダラカが病原体を媒介して感染する。",
          "tags": [
            "マラリア",
            "媒介動物",
            "感染経路"
          ],
          "importance": 2,
          "isPremium": true
        },
        {
          "question": "感染症の予防で最も基本的な方法はどれか？",
          "choices": [
            "手洗いとうがい",
            "抗生物質の服用",
            "栄養剤の摂取",
            "運動の強化"
          ],
          "answerIndex": 0,
          "explanation": "手洗いやうがいは多くの感染症予防の基本である。",
          "tags": [
            "予防",
            "衛生",
            "基本対策"
          ],
          "importance": 1,
          "isPremium": true
        },
        {
          "question": "パンデミックとはどのような状態を指すか？",
          "choices": [
            "世界的に感染症が大流行している状態",
            "一つの地域でのみ感染が見られる状態",
            "感染者が一時的に増える状態",
            "季節ごとに流行を繰り返す状態"
          ],
          "answerIndex": 0,
          "explanation": "パンデミックは感染症が国や地域を越えて世界的に流行することをいう。",
          "tags": [
            "パンデミック",
            "流行",
            "国際"
          ],
          "importance": 1,
          "isPremium": true
        },
        {
          "question": "感染症の拡大を防ぐために社会全体で必要なことはどれか？",
          "choices": [
            "情報共有と協力体制の構築",
            "個人の責任に任せる",
            "医療機関の数を減らす",
            "感染者を非難する"
          ],
          "answerIndex": 0,
          "explanation": "感染症対策では個人だけでなく社会全体での連携と支援が重要である。",
          "tags": [
            "社会的支援",
            "公衆衛生",
            "協働"
          ],
          "importance": 2,
          "isPremium": true
        },
        {
          "question": "抗菌薬が効かなくなる現象を何というか？",
          "choices": [
            "薬剤耐性",
            "免疫低下",
            "耐寒性",
            "抵抗力増強"
          ],
          "answerIndex": 0,
          "explanation": "抗菌薬を過剰に使うと薬剤耐性菌が生まれ感染治療が困難になる。",
          "tags": [
            "薬剤耐性",
            "抗菌薬",
            "公衆衛生"
          ],
          "importance": 2,
          "isPremium": true
        },
        {
          "question": "感染症の「感染源」に当てはまるものはどれか？",
          "choices": [
            "病原体を持つ人や動物",
            "ウイルスのない空気",
            "汚染されていない水",
            "健康な植物"
          ],
          "answerIndex": 0,
          "explanation": "感染源とは病原体を保有して感染を広げる人や動物を指す。",
          "tags": [
            "感染源",
            "病原体",
            "感染経路"
          ],
          "importance": 1,
          "isPremium": true
        },
        {
          "question": "感染症の「感染経路」を断つために有効なのはどれか？",
          "choices": [
            "消毒やマスクの使用",
            "食事の制限",
            "運動量の調整",
            "読書習慣の維持"
          ],
          "answerIndex": 0,
          "explanation": "感染経路の遮断には消毒やマスク着用などが有効である。",
          "tags": [
            "感染予防",
            "衛生",
            "遮断"
          ],
          "importance": 1,
          "isPremium": true
        },
        {
          "question": "感染症に対する「感受性者対策」として正しいのはどれか？",
          "choices": [
            "予防接種を受ける",
            "手洗いをしない",
            "感染者に近づく",
            "免疫を下げる薬を飲む"
          ],
          "answerIndex": 0,
          "explanation": "ワクチン接種は感受性者対策の代表的な方法である。",
          "tags": [
            "予防接種",
            "免疫",
            "対策"
          ],
          "importance": 1,
          "isPremium": true
        },
        {
          "question": "情報の偏りや誤情報による感染不安を何というか？",
          "choices": [
            "インフォデミック",
            "アカデミック",
            "パンデミック",
            "エピデミック"
          ],
          "answerIndex": 0,
          "explanation": "インフォデミックは感染症に関する不正確な情報が広がる現象を指す。",
          "tags": [
            "インフォデミック",
            "情報",
            "心理"
          ],
          "importance": 3,
          "isPremium": true
        },
        {
          "question": "「One World」という考え方の目的はどれか？",
          "choices": [
            "地球全体の健康を共有して守ること",
            "国ごとに健康格差を広げること",
            "動物の健康のみを重視すること",
            "環境問題を軽視すること"
          ],
          "answerIndex": 0,
          "explanation": "One Worldは人・動物・環境を一体として世界全体の健康を守る考えである。",
          "tags": [
            "OneWorld",
            "国際保健",
            "SDH"
          ],
          "importance": 3,
          "isPremium": true
        },
        {
          "question": "感染症が発生しても社会機能を維持するために重要なことはどれか？",
          "choices": [
            "医療・物流などの継続計画を立てること",
            "学校をすぐに閉鎖すること",
            "感染者を全員隔離すること",
            "他国との交流を完全に断つこと"
          ],
          "answerIndex": 0,
          "explanation": "感染症流行時でも社会基盤を維持するためBCP（事業継続計画）が重要である。",
          "tags": [
            "感染症対策",
            "社会機能",
            "危機管理"
          ],
          "importance": 3,
          "isPremium": true
        },
        {
          "question": "感染症の流行を抑えるために有効なワクチン接種率のことを何というか？",
          "choices": [
            "集団免疫",
            "自然免疫",
            "獲得免疫",
            "自己免疫"
          ],
          "answerIndex": 0,
          "explanation": "集団免疫は一定割合の人が免疫を持つことで流行を防ぐ仕組みである。",
          "tags": [
            "免疫",
            "集団免疫",
            "予防"
          ],
          "importance": 2,
          "isPremium": true
        },
        {
          "question": "感染症対策におけるグローバル化の課題として正しいものはどれか？",
          "choices": [
            "人や物の移動により感染症が広がりやすくなる",
            "感染症が国境で完全に止まる",
            "世界中で感染症が減少する",
            "感染経路が単純になる"
          ],
          "answerIndex": 0,
          "explanation": "国際交流の拡大により感染症は短期間で世界中に拡大するリスクがある。",
          "tags": [
            "グローバル化",
            "感染拡大",
            "国際保健"
          ],
          "importance": 2,
          "isPremium": true
        },
        {
          "question": "感染症流行時に差別や偏見が生じる原因として適切なのはどれか？",
          "choices": [
            "誤った情報や不安による行動",
            "感染者への理解の深さ",
            "正確な情報提供",
            "冷静な対応"
          ],
          "answerIndex": 0,
          "explanation": "恐怖やデマが差別や偏見を引き起こすことがある。",
          "tags": [
            "差別",
            "情報",
            "社会問題"
          ],
          "importance": 3,
          "isPremium": true
        },
        {
          "question": "感染症の問題に対して私たちが取るべき基本的姿勢はどれか？",
          "choices": [
            "科学的根拠に基づいて冷静に行動する",
            "うわさや感情で判断する",
            "感染者を避けて関係を断つ",
            "予防行動をとらない"
          ],
          "answerIndex": 0,
          "explanation": "感染症対策では正確な情報をもとに冷静な行動を取ることが大切である。",
          "tags": [
            "健康行動",
            "科学的思考",
            "感染症"
          ],
          "importance": 3,
          "isPremium": true
        }
      ]
    }
  ]
}